reflec/__init__.py
reflec/mul.py
reflec-0.0.1.dist-info/METADATA
reflec-0.0.1.dist-info/WHEEL
reflec-0.0.1.dist-info/top_level.txt
reflec-0.0.1.dist-info/RECORD
